atgql/__init__.py
atgql-0.1.0.dist-info/LICENSE
atgql-0.1.0.dist-info/WHEEL
atgql-0.1.0.dist-info/METADATA
atgql-0.1.0.dist-info/RECORD
