Metadata-Version: 2.1
Name: atgql
Version: 0.1.0
Summary: A Python port of graphql-js and dataloader
License: MIT
Author: iyanging
Author-email: iyanging@163.com
Requires-Python: >=3.9,<4.0
Classifier: License :: OSI Approved :: MIT License
Classifier: Programming Language :: Python :: 3
Classifier: Programming Language :: Python :: 3.9
